lookahead_keys_attention/__init__.py
lookahead_keys_attention/lookahead_keys_attention.py
lookahead_keys_attention/lookahead_keys_attention_triton.py
lookahead_keys_attention-0.1.2.dist-info/METADATA
lookahead_keys_attention-0.1.2.dist-info/WHEEL
lookahead_keys_attention-0.1.2.dist-info/licenses/LICENSE
lookahead_keys_attention-0.1.2.dist-info/RECORD
