Metadata-Version: 2.4
Name: lookahead-keys-attention
Version: 0.1.2
Summary: Lookahead Keys Attention
Project-URL: Homepage, https://pypi.org/project/lookahead-keys-attention/
Project-URL: Repository, https://github.com/lucidrains/lookahead-keys-attention
Author-email: Phil Wang <lucidrains@gmail.com>
License: MIT License
License-File: LICENSE
Keywords: artificial intelligence,attention mechanism,deep learning,multi-modal transformer
Classifier: Development Status :: 4 - Beta
Classifier: Intended Audience :: Developers
Classifier: License :: OSI Approved :: MIT License
Classifier: Programming Language :: Python :: 3.9
Classifier: Topic :: Scientific/Engineering :: Artificial Intelligence
Requires-Python: >=3.9
Requires-Dist: einops>=0.8.1
Requires-Dist: rotary-embedding-torch>=0.8.9
Requires-Dist: torch>=2.4
Provides-Extra: examples
Provides-Extra: test
Requires-Dist: pytest; extra == 'test'
